boba_fetch/__init__.py
boba_fetch/cli.py
boba_fetch/log.py
boba_fetch/poller.py
boba_fetch/process.py
boba_fetch/rpc.py
boba_fetch/syncer.py
boba_fetch/tracker.py
boba_fetch-0.2.8.dist-info/entry_points.txt
boba_fetch-0.2.8.dist-info/WHEEL
boba_fetch-0.2.8.dist-info/METADATA
boba_fetch-0.2.8.dist-info/RECORD
