Metadata-Version: 2.1
Name: boba-fetch
Version: 0.2.8
Summary: A script for repeatedly polling files on a remote host using SSH and then downloading them using rsync.
License: GPL-3.0-or-later
Author-email: Eugene Kovalev <eugene@kovalev.systems>
Requires-Python: >=3.8
Requires-Dist: click>=8.0.3
Requires-Dist: fabric>=2.6.0
Requires-Dist: logzero>=1.7.0
Requires-Dist: secretstorage>=3.3.1
Requires-Dist: types-setuptools>=57.4.9
Project-URL: documentation, https://gitlab.com/abraxos/boba
Project-URL: homepage, https://gitlab.com/abraxos/boba
Project-URL: repository, https://gitlab.com/abraxos/boba
